icortex/__init__.py
icortex/cli.py
icortex/config.py
icortex/context.py
icortex/defaults.py
icortex/helper.py
icortex/init.py
icortex/kernel/__init__.py
icortex/kernel/__main__.py
icortex/kernel/app.py
icortex/kernel/icortex/kernel.json
icortex/kernel/icortex/logo-128x128.png
icortex/kernel/icortex/logo-256x256.png
icortex/kernel/icortex/logo-32x32.png
icortex/kernel/icortex/logo-512x512.png
icortex/kernel/icortex/logo-64x64.png
icortex/kernel/icortex/logo-svg.svg
icortex/kernel/install.py
icortex/magics.py
icortex/parser.py
icortex/pypi.py
icortex/services/__init__.py
icortex/services/echo.py
icortex/services/generation_result.py
icortex/services/huggingface.py
icortex/services/openai.py
icortex/services/service_base.py
icortex/services/service_interaction.py
icortex/services/textcortex.py
icortex/var.py
icortex-0.1.4.dist-info/LICENSE
icortex-0.1.4.dist-info/WHEEL
icortex-0.1.4.dist-info/entry_points.txt
icortex-0.1.4.dist-info/METADATA
icortex-0.1.4.dist-info/RECORD
