Metadata-Version: 2.1
Name: icortex
Version: 0.1.4
Summary: Jupyter kernel that can generate Python code from natural language prompts
Home-page: https://icortex.ai/
License: Apache
Keywords: copilot,tabnine,codex,openai,code generation,code completion,generate code,natural language to python,icortex,textcortex,gpt-3,codegen,polycoder,jupyter notebook,smart jupyter notebook,jupyter notebook kernel,icortex kernel
Author: TextCortex Team
Author-email: onur@textcortex.com
Requires-Python: >=3.7.1,<4
Classifier: Intended Audience :: Developers
Classifier: Intended Audience :: Education
Classifier: Intended Audience :: Science/Research
Classifier: License :: OSI Approved :: Apache Software License
Classifier: License :: Other/Proprietary License
Classifier: Operating System :: OS Independent
Classifier: Programming Language :: Python :: 3
Classifier: Programming Language :: Python :: 3.8
Classifier: Programming Language :: Python :: 3.9
Classifier: Programming Language :: Python :: 3.10
Classifier: Programming Language :: Python :: 3.11
Classifier: Programming Language :: Python :: 3
Classifier: Programming Language :: Python :: 3.10
Classifier: Programming Language :: Python :: 3.7
Classifier: Programming Language :: Python :: 3.8
Classifier: Programming Language :: Python :: 3.9
Classifier: Topic :: Scientific/Engineering :: Artificial Intelligence
Provides-Extra: huggingface
Provides-Extra: openai
Requires-Dist: Pygments (>=2.13.0,<3.0.0)
Requires-Dist: black (>=22.1,<23.0)
Requires-Dist: entrypoints (>=0.4,<0.5)
Requires-Dist: importlib-metadata (>=4.0.0)
Requires-Dist: ipykernel (>=6.16.0,<7.0.0)
Requires-Dist: ipython (>=7.0.0)
Requires-Dist: ipywidgets (>=8.0.2,<9.0.0)
Requires-Dist: jupyter-client (>=7.4.2,<8.0.0)
Requires-Dist: jupyter-console (>=6.4.4,<7.0.0)
Requires-Dist: jupyter-core (>=4.11.1,<5.0.0)
Requires-Dist: jupyterlab-widgets (>=3.0.3,<4.0.0)
Requires-Dist: onnx (>=1.12.0,<2.0.0) ; extra == "huggingface"
Requires-Dist: onnxruntime (>=1.12.1,<2.0.0) ; extra == "huggingface"
Requires-Dist: openai (>=0.23.1,<0.24.0) ; extra == "openai"
Requires-Dist: optimum (>=1.4.0,<2.0.0) ; extra == "huggingface"
Requires-Dist: requests (>=2.0,<3.0)
Requires-Dist: toml (>=0.10.2,<0.11.0)
Requires-Dist: torch (>=1.12.1,<2.0.0) ; extra == "huggingface"
Requires-Dist: transformers (>=4.23.1,<5.0.0) ; extra == "huggingface"
Requires-Dist: urllib3 (>=1.0,<2.0)
Project-URL: Repository, https://github.com/textcortex/icortex
